aioscheduler_deskent/__init__.py
aioscheduler_deskent/__main__.py
aioscheduler_deskent/aioscheduler.py
aioscheduler_deskent/exceptions.py
aioscheduler_deskent-0.0.9.dist-info/LICENSE
aioscheduler_deskent-0.0.9.dist-info/METADATA
aioscheduler_deskent-0.0.9.dist-info/WHEEL
aioscheduler_deskent-0.0.9.dist-info/top_level.txt
aioscheduler_deskent-0.0.9.dist-info/RECORD
