Metadata-Version: 2.1
Name: aioscheduler-deskent
Version: 0.0.9
Summary: AIOScheduler
Home-page: https://github.com/Deskent/aioscheduler_deskent
Author: Deskent
Classifier: Programming Language :: Python :: 3
Classifier: License :: OSI Approved :: MIT License
Classifier: Operating System :: OS Independent
Requires-Python: >=3.7
License-File: LICENSE
